.gitignore
.gitlab-ci.yml
AUTHORS
CMakeLists.txt
COPYING
INSTALL
README.md
TODO
config.h.cmake
dune-alugrid.pc.in
dune.module
pyproject.toml
setup.py
cmake/modules/AlugridTortureTests.cmake
cmake/modules/CMakeLists.txt
cmake/modules/DuneAlugridMacros.cmake
cmake/modules/FindDLMalloc.cmake
cmake/modules/FindPThreads.cmake
cmake/modules/FindSIONlib.cmake
cmake/modules/FindZOLTAN.cmake
doc/CMakeLists.txt
doc/dunealugrid.bib
doc/hexahedron_alugrid.svg
doc/hexahedron_edges_alugrid.svg
doc/tetrahedron_alugrid.svg
doc/tetrahedron_edges_alugrid.svg
doc/doxygen/CMakeLists.txt
doc/doxygen/Doxylocal
doc/doxygen/mainpage.txt
dune/CMakeLists.txt
dune/alugrid/CMakeLists.txt
dune/alugrid/dgf.hh
dune/alugrid/grid.hh
dune/alugrid/3d/CMakeLists.txt
dune/alugrid/3d/alu3dinclude.hh
dune/alugrid/3d/alu3diterators.hh
dune/alugrid/3d/alu3diterators_imp.cc
dune/alugrid/3d/alugrid.hh
dune/alugrid/3d/aluinline.hh
dune/alugrid/3d/communication.hh
dune/alugrid/3d/datacollectorcaps.hh
dune/alugrid/3d/datahandle.hh
dune/alugrid/3d/entity.hh
dune/alugrid/3d/entity_imp.cc
dune/alugrid/3d/entity_inline.hh
dune/alugrid/3d/entityseed.hh
dune/alugrid/3d/faceutility.cc
dune/alugrid/3d/faceutility.hh
dune/alugrid/3d/faceutility_imp.cc
dune/alugrid/3d/geometry.hh
dune/alugrid/3d/geometry_imp.cc
dune/alugrid/3d/grid.hh
dune/alugrid/3d/grid_imp.cc
dune/alugrid/3d/grid_inline.hh
dune/alugrid/3d/gridfactory.cc
dune/alugrid/3d/gridfactory.hh
dune/alugrid/3d/gridview.hh
dune/alugrid/3d/indexsets.cc
dune/alugrid/3d/indexsets.hh
dune/alugrid/3d/iterator.cc
dune/alugrid/3d/iterator.hh
dune/alugrid/3d/iterator_imp.cc
dune/alugrid/3d/mappings.cc
dune/alugrid/3d/mappings.hh
dune/alugrid/3d/mappings_imp.cc
dune/alugrid/3d/topology.cc
dune/alugrid/3d/topology.hh
dune/alugrid/common/CMakeLists.txt
dune/alugrid/common/alugrid_assert.hh
dune/alugrid/common/backuprestore.hh
dune/alugrid/common/bisectioncompatibility.hh
dune/alugrid/common/bndprojection.hh
dune/alugrid/common/capabilities.hh
python/dune_alugrid.egg-info/PKG-INFO
python/dune_alugrid.egg-info/SOURCES.txt
python/dune_alugrid.egg-info/dependency_links.txt
python/dune_alugrid.egg-info/requires.txt
python/dune_alugrid.egg-info/top_level.txt
