Metadata-Version: 2.1
Name: dune-alugrid
Version: 2.10.0
Summary: Module providing the DUNE grid interface for unstructured simplicial and cube grids in 2 and 3 space dimensions
Home-page: https://gitlab.dune-project.org/extensions/dune-alugrid
Author: Robert Kloefkorn, Martin Alkaemper, Andreas Dedner and Martin Nolte
Author-email: dune-devel@lists.dune-project.org
Classifier: Programming Language :: C++
Classifier: Programming Language :: Python :: 3
Classifier: License :: OSI Approved :: GNU General Public License (GPL)
Requires-Python: >=3.4
License-File: COPYING
License-File: AUTHORS
